atomInSmiles/__init__.py
atomInSmiles/atomInSmiles.py
atomInSmiles-1.0.2.dist-info/LICENSE.md
atomInSmiles-1.0.2.dist-info/METADATA
atomInSmiles-1.0.2.dist-info/WHEEL
atomInSmiles-1.0.2.dist-info/top_level.txt
atomInSmiles-1.0.2.dist-info/zip-safe
atomInSmiles-1.0.2.dist-info/RECORD
