Metadata-Version: 2.1
Name: atomInSmiles
Version: 1.0.2
Summary: Atom-in-SMILES tokenizer for SMILES strings
Home-page: https://github.com/snu-lcbc/atom-in-SMILES
Author: Islambek Ashyrmamatov, Umit V. Ucak,  Juyong Lee
Author-email: ashyrmamatov01@gmail.com
License: Creative Commons Attribution-NonCommercial 4.0 International (CC BY-NC 4.0)
Requires-Python: >=3.8
License-File: LICENSE.md
Requires-Dist: rdkit (>=2022.9.5)
